MANIFEST.in
README.rst
pyproject.toml
requirements.txt
setup.cfg
setup.py
t_bug_catcher/__init__.py
t_bug_catcher/bug_catcher.py
t_bug_catcher/bug_snag.py
t_bug_catcher/config.py
t_bug_catcher/exceptions.py
t_bug_catcher/jira.py
t_bug_catcher/stack_saver.py
t_bug_catcher/workitems.py
t_bug_catcher.egg-info/PKG-INFO
t_bug_catcher.egg-info/SOURCES.txt
t_bug_catcher.egg-info/dependency_links.txt
t_bug_catcher.egg-info/not-zip-safe
t_bug_catcher.egg-info/requires.txt
t_bug_catcher.egg-info/top_level.txt
t_bug_catcher/resources/whispers_config.yml
t_bug_catcher/utils/__init__.py
t_bug_catcher/utils/common.py
t_bug_catcher/utils/logger.py
tests/test_jira_grouping.py
tests/test_t_bug_catcher.py